Luke001/__init__.py
Luke001/main.py
Luke001-0.0.3.dist-info/METADATA
Luke001-0.0.3.dist-info/WHEEL
Luke001-0.0.3.dist-info/top_level.txt
Luke001-0.0.3.dist-info/RECORD
